setup.cfg
setup.py
yanport_client/__init__.py
yanport_client/api_client.py
yanport_client/configuration.py
yanport_client/rest.py
yanport_client.egg-info/PKG-INFO
yanport_client.egg-info/SOURCES.txt
yanport_client.egg-info/dependency_links.txt
yanport_client.egg-info/requires.txt
yanport_client.egg-info/top_level.txt
yanport_client/apis/__init__.py
yanport_client/apis/agences_api.py
yanport_client/apis/annonces_api.py
yanport_client/apis/biens_api.py
yanport_client/apis/bienssimilaires_api.py
yanport_client/apis/encadrementloyers_api.py
yanport_client/apis/etudes_api.py
yanport_client/apis/evenementsadbox_api.py
yanport_client/apis/mandataires_api.py
yanport_client/apis/utilisateurs_api.py
yanport_client/apis/villes_api.py
yanport_client/models/__init__.py
yanport_client/models/ad.py
yanport_client/models/ad_ref.py
yanport_client/models/address.py
yanport_client/models/agency.py
yanport_client/models/agency_naf_code.py
yanport_client/models/body.py
yanport_client/models/body_1.py
yanport_client/models/body_2.py
yanport_client/models/bound_type.py
yanport_client/models/building.py
yanport_client/models/city.py
yanport_client/models/count_response.py
yanport_client/models/crawl_source.py
yanport_client/models/customer.py
yanport_client/models/date_histogram.py
yanport_client/models/date_histogram_point.py
yanport_client/models/dealer_sub_type.py
yanport_client/models/dealer_type.py
yanport_client/models/default_response.py
yanport_client/models/event_type.py
yanport_client/models/histogram.py
yanport_client/models/histogram_point.py
yanport_client/models/inline_response_200.py
yanport_client/models/inline_response_200_1.py
yanport_client/models/inline_response_200_2.py
yanport_client/models/inline_response_200_3.py
yanport_client/models/inline_response_200_4.py
yanport_client/models/inline_response_200_5.py
yanport_client/models/inline_response_200_6.py
yanport_client/models/inline_response_200_7.py
yanport_client/models/iris_quarter.py
yanport_client/models/lng_lat.py
yanport_client/models/location.py
yanport_client/models/mandatary_network.py
yanport_client/models/marketing_dealer.py
yanport_client/models/marketing_type.py
