Metadata-Version: 1.0
Name: yanport-client
Version: 1.0.0
Summary: Yanport API client library
Home-page: UNKNOWN
Author: UNKNOWN
Author-email: dev@yanport.com
License: UNKNOWN
Keywords: Swagger,Yanport API
Platform: UNKNOWN
